ProgramizCYuyanJiaochengChuyiFix1/README.md
ProgramizCYuyanJiaochengChuyiFix1/__init__.py
ProgramizCYuyanJiaochengChuyiFix1/__main__.py
ProgramizCYuyanJiaochengChuyiFix1/file.epub
ProgramizCYuyanJiaochengChuyiFix1/index.html
ProgramizCYuyanJiaochengChuyiFix1/css/__init__.py
ProgramizCYuyanJiaochengChuyiFix1/css/annotations.css
ProgramizCYuyanJiaochengChuyiFix1/css/main.css
ProgramizCYuyanJiaochengChuyiFix1/css/normalize.css
ProgramizCYuyanJiaochengChuyiFix1/css/popup.css
ProgramizCYuyanJiaochengChuyiFix1/font/__init__.py
ProgramizCYuyanJiaochengChuyiFix1/font/fontello.eot
ProgramizCYuyanJiaochengChuyiFix1/font/fontello.svg
ProgramizCYuyanJiaochengChuyiFix1/font/fontello.ttf
ProgramizCYuyanJiaochengChuyiFix1/font/fontello.woff
ProgramizCYuyanJiaochengChuyiFix1/img/__init__.py
ProgramizCYuyanJiaochengChuyiFix1/img/annotator-glyph-sprite.png
ProgramizCYuyanJiaochengChuyiFix1/img/annotator-icon-sprite.png
ProgramizCYuyanJiaochengChuyiFix1/img/apple-touch-icon.png
ProgramizCYuyanJiaochengChuyiFix1/img/cancelfullscreen.png
ProgramizCYuyanJiaochengChuyiFix1/img/close.png
ProgramizCYuyanJiaochengChuyiFix1/img/fullscreen.png
ProgramizCYuyanJiaochengChuyiFix1/img/loader.gif
ProgramizCYuyanJiaochengChuyiFix1/img/menu-icon.png
ProgramizCYuyanJiaochengChuyiFix1/img/save.png
ProgramizCYuyanJiaochengChuyiFix1/img/saved.png
ProgramizCYuyanJiaochengChuyiFix1/img/settings-s.png
ProgramizCYuyanJiaochengChuyiFix1/img/settings.png
ProgramizCYuyanJiaochengChuyiFix1/img/star.png
ProgramizCYuyanJiaochengChuyiFix1/js/__init__.py
ProgramizCYuyanJiaochengChuyiFix1/js/epub.js
ProgramizCYuyanJiaochengChuyiFix1/js/epub.min.js
ProgramizCYuyanJiaochengChuyiFix1/js/epub.min.map
ProgramizCYuyanJiaochengChuyiFix1/js/hooks.min.js
ProgramizCYuyanJiaochengChuyiFix1/js/hooks.min.map
ProgramizCYuyanJiaochengChuyiFix1/js/reader.js
ProgramizCYuyanJiaochengChuyiFix1/js/reader.js.map
ProgramizCYuyanJiaochengChuyiFix1/js/reader.min.js
ProgramizCYuyanJiaochengChuyiFix1/js/reader.min.map
programiz_c_yuyan_jiaocheng_chuyi_fix1-2025.3.24.1.dist-info/METADATA
programiz_c_yuyan_jiaocheng_chuyi_fix1-2025.3.24.1.dist-info/WHEEL
programiz_c_yuyan_jiaocheng_chuyi_fix1-2025.3.24.1.dist-info/entry_points.txt
programiz_c_yuyan_jiaocheng_chuyi_fix1-2025.3.24.1.dist-info/top_level.txt
programiz_c_yuyan_jiaocheng_chuyi_fix1-2025.3.24.1.dist-info/RECORD
